[
    {
        "objectHeader": "Amazon Cognito",
        "objectIcon": "star-border",
        "objectDescription": "description for badge",
        "objectLink": "https//:google.com/",
        "objectBadgeCreator": "badge creator",
        "objectTimeETA": "4.00 hours",
        "objectStepIcon": "star-border",
        "objectStepDescription": "Creating you first lambda function",
        "objectStepTime": "2.00 hours"
    },
    {
        "objectHeader": "Amazon I AM",
        "objectIcon": "star-border",
        "objectDescription": "description for badge",
        "objectLink": "https//:google.com/",
        "objectBadgeCreator": "badge creator",
        "objectTimeETA": "4.00 hours",
        "objectStepIcon": "star-border",
        "objectStepDescription": "Creating you first lambda function",
        "objectStepTime": "2.00 hours"
    },
    {
        "objectHeader": "Signing up for AWS Web Services", 
        "objectIcon": "star-border",
        "objectDescription": "description for badge",
        "objectLink": "https//:google.com/",
        "objectBadgeCreator": "badge creator",
        "objectTimeETA": "4.00 hours",
        "objectStepIcon": "star-border",
        "objectStepDescription": "Creating you first lambda function",
        "objectStepTime": "2.00 hours"
    },
    {
        "objectHeader": "AWS - LAMDA Phase 1", 
        "objectIcon": "star-border",
        "objectDescription": "description for badge",
        "objectLink": "https//:google.com/",
        "objectBadgeCreator": "badge creator",
        "objectTimeETA": "4.00 hours",
        "objectStepIcon": "star-border",
        "objectStepDescription": "Creating you first lambda function",
        "objectStepTime": "2.00 hours"
    },
    {
        "objectHeader": "Amazon S3 Phase 1", 
        "objectIcon": "star-border",
        "objectDescription": "description for badge",
        "objectLink": "https//:google.com/",
        "objectBadgeCreator": "badge creator",
        "objectTimeETA": "4.00 hours",
        "objectStepIcon": "star-border",
        "objectStepDescription": "Creating you first lambda function",
        "objectStepTime": "2.00 hours"
    }
]